{
  "VNINDEX": {
    "symbol": "VNINDEX",
    "date": "2026-06-30 10:29 (ICT)",
    "close": 1857.45,
    "change": 2.480000000000018,
    "change_pc": 0.13369488455339,
    "volume": 157783682.0,
    "technical": {
      "ma20": 1829.3914999999997,
      "pivot": 1858.8966666666668,
      "cmf": 0.1636886858365171,
      "adx": 21.465439554817326
    },
    "general_markdown": "### 1. Diễn biến phiên giao dịch\nVNINDEX đóng cửa tại 1857.45, biến động nhẹ so với tham chiếu. Khối lượng khớp lệnh đạt 157.784 triệu CP, thấp hơn 74.03% so với trung bình 20 phiên.\n\n### 2. Xu hướng & Động lượng\n- Xu hướng ngắn hạn (MA10, MA20): tăng\n- Xu hướng trung hạn (MA50): giảm\n- Xu hướng dài hạn (MA100, MA200): tăng\n- ROC10 = +2.74%, ROC20 = +1.70%: động lượng tích cực\n- Tổng hợp: Chỉ số đang trong vùng phân kỳ xu hướng (ngắn=up, trung=down, dài=up)\n\n### 3. Nhận định Xu hướng Tổng hợp\n**Mở đầu:** Thị trường đang trong tình trạng hỗn hợp (ngắn=up, trung=down, dài=up), với động lượng tích cực từ ROC nhưng xu hướng trung hạn vẫn giảm.\n\n**Độ rộng thị trường:** Bên mua chiếm ưu thế với tỷ lệ A/D = 1.8 (63 mã tăng, 35 mã giảm), cho thấy đà tăng lan tỏa rộng.\n\n**Thanh khoản:** Khối lượng 157.78 triệu CP thấp hơn 74.03% so TB 20 phiên, cho thấy dòng tiền rất thận trọng.\n\n**Sức khỏe thị trường:** Giá đang trên MA10, MA20, MA100, MA200 nhưng dưới MA50. Tỷ lệ A/D tích cực cho thấy phục hồi có lan tỏa nhưng chưa vượt được kháng cự trung hạn.\n\n**Khuyến nghị hành động:**\n- *Cảnh báo:* ADX ở mức 21.5 (trung bình), CMF dương 0.1637 nhưng khối lượng thấp, cần thận trọng.\n- *Chiến lược:* Chờ tín hiệu.\n\n**Kết luận:** ➡️ **Tạm đứng ngoài** — thị trường phân kỳ xu hướng, thanh khoản yếu, cần chờ tín hiệu xác nhận rõ ràng hơn.\n\n### 4. Thống kê Cổ phiếu & Nhóm ngành\n**Top 5 tăng mạnh nhất (VNINDEX):** TRC (+6.93%), NKG (+2.08%), OCB (+1.83%), PET (+1.65%), TVS (+1.37%)\n**Top 5 giảm mạnh nhất (VNINDEX):** APG (-1.05%), EVF (-1.14%), BIC (-1.69%), LBM (-2.03%), PTB (-2.33%)\n**Nhóm ngành thu hút dòng tiền:** Cao su - Gỗ (+1.03%), Dầu khí (+0.60%), Hóa chất - Phân bón (+0.41%), Thép - Xây dựng (+0.28%), Ngân hàng (+0.22%)\n**Nhóm ngành bị rút dòng tiền:** Thủy sản (-0.03%), Điện - Nước - Khí (-0.09%), Khoáng sản (-0.14%), Bán lẻ - Tiêu dùng (-0.17%), Dệt may - Da giày (-0.22%), Công nghệ - Viễn thông (-0.25%), Bảo hiểm (-1.06%)\n\n### 5. Market Breadth & Độ rộng thị trường\nVNINDEX: Tăng 63, Giảm 35, Đứng 56; Tỷ lệ A/D = 1.8. VN30: Tăng 16, Giảm 4, Đứng 10; Tỷ lệ A/D = 4.0. Thị trường phân hóa, bên mua chiếm ưu thế nhưng chưa đồng thuận mạnh.",
    "scenario_markdown": "### 1. KỊCH BẢN TÍCH CỰC (Xác suất cao nhất)\n* **Xác suất xảy ra:** 45%\n* **Độ tin cậy:** 6/10\n\n**Điều kiện kích hoạt:**\n- Giá vượt dứt khoát kháng cự MA50 (1858.88) với độ rộng thị trường tích cực.\n- Khối lượng cải thiện rõ rệt, vượt trên TB 20 phiên.\n\n### 2. KỊCH BẢN TRUNG TÍNH (Dao động trong range 1844.66 - 1859.39)\n* **Xác suất xảy ra:** 35%\n* **Độ tin cậy:** 7/10\n\n**Điều kiện kích hoạt:**\n- Giá tiếp tục dao động, không thể vượt 1859.39 nhưng cũng không thủng 1844.66.\n- Biến động duy trì ở mức LOW_VOL và Trend Agreement Score duy trì dưới mức 50.\n\n### 3. KỊCH BẢN TIÊU CỰC\n* **Xác suất xảy ra:** 20%\n* **Độ tin cậy:** 5/10\n\n**Điều kiện kích hoạt:**\n- Giá thủng dứt khoát hỗ trợ 1844.66 với khối lượng lớn, độ rộng thị trường tiêu cực.\n- Giá đóng cửa dưới MA10 (1851.36).\n\n### Dẫn chứng chung cho các kịch bản:\n- **Volatility regime = LOW_VOL:** Biên độ dao động (20 phiên) ≈ 6.41% của giá, hỗ trợ cho kịch bản sideway biên độ rộng.\n- **Trend agreement score = 44/100 (BULLISH):** Cho thấy xu hướng tăng vẫn chi phối, khiến mọi đợt chỉnh khó bền vững.\n- **Khoảng đệm kỹ thuật:** Khoảng cách tới hỗ trợ/kháng cự hiện tại là -0.69% / 0.10% cho thấy thị trường đang ở vị trí sát vùng ranh giới quan trọng.\n- **Horizon (Tầm nhìn):** 5-15 phiên.",
    "volume_markdown": "### 1. Thống kê Chỉ báo Khối lượng\n| Chỉ báo | Giá trị | Nhận định |\n|---|---|---|\n| CMF | 0.1637 | Dòng tiền vào |\n| VWAP | 1833.55 | Giá trên VWAP, xu hướng tích cực |\n| OBV | 53923562197 | Khối lượng tích lũy tăng |\n\n### 2. Nhận định Dòng tiền\nDòng tiền ròng vào thị trường (CMF > 0). Giá giao dịch trên VWAP cho thấy áp lực mua chiếm ưu thế. Không có dấu hiệu phân phối rõ rệt.",
    "trend_markdown": "### 1. Thống kê Xu hướng & Động lượng\n| Chỉ báo | Giá trị | Khoảng cách % | Vai trò |\n|---|---|---|---|\n| MA10 | 1851.36 | +0.33% | Hỗ trợ |\n| MA20 | 1829.39 | +1.53% | Hỗ trợ |\n| MA50 | 1858.88 | -0.08% | Kháng cự |\n| MA100 | 1803.48 | +2.99% | Hỗ trợ |\n| MA200 | 1760.55 | +5.50% | Hỗ trợ |\n| ROC10 | +2.74% | - | Động lượng tích cực |\n| ADX | 21.47 | - | Xu hướng trung bình |\n| ATR | 26.52",
    "tas": {
      "score": 44,
      "label": "BULLISH",
      "total_raw": 4,
      "max_raw": 9,
      "indicators": [
        {
          "group": "Cấu trúc (MA)",
          "name": "Giá vs MA20 (1829)",
          "status": "Bullish",
          "score": 1
        },
        {
          "group": "Cấu trúc (MA)",
          "name": "Giá vs MA50 (1859)",
          "status": "Bearish",
          "score": -1
        },
        {
          "group": "Cấu trúc (MA)",
          "name": "Giá vs MA200 (1761)",
          "status": "Bullish",
          "score": 1
        },
        {
          "group": "Động lượng",
          "name": "ROC10 (+2.7%)",
          "status": "Bullish",
          "score": 1
        },
        {
          "group": "Động lượng",
          "name": "ROC20 (+1.7%)",
          "status": "Neutral",
          "score": 0
        },
        {
          "group": "Động lượng",
          "name": "Keltner (1805–1852)",
          "status": "Bullish",
          "score": 1
        },
        {
          "group": "Dòng tiền",
          "name": "CMF (+0.164)",
          "status": "Bullish",
          "score": 1
        },
        {
          "group": "Dòng tiền",
          "name": "Giá vs VWAP (1834)",
          "status": "Bullish",
          "score": 1
        },
        {
          "group": "Dòng tiền",
          "name": "Vol vs MA20 (-74%)",
          "status": "Bearish",
          "score": -1
        }
      ],
      "history": [
        {
          "date": "2026-06-03",
          "score": -25,
          "label": "WEAK BEARISH"
        },
        {
          "date": "2026-06-04",
          "score": -25,
          "label": "WEAK BEARISH"
        },
        {
          "date": "2026-06-05",
          "score": -25,
          "label": "WEAK BEARISH"
        },
        {
          "date": "2026-06-08",
          "score": 0,
          "label": "NEUTRAL"
        },
        {
          "date": "2026-06-09",
          "score": -25,
          "label": "WEAK BEARISH"
        },
        {
          "date": "2026-06-10",
          "score": -25,
          "label": "WEAK BEARISH"
        },
        {
          "date": "2026-06-11",
          "score": -25,
          "label": "WEAK BEARISH"
        },
        {
          "date": "2026-06-12",
          "score": 0,
          "label": "NEUTRAL"
        },
        {
          "date": "2026-06-15",
          "score": 25,
          "label": "WEAK BULLISH"
        },
        {
          "date": "2026-06-16",
          "score": 0,
          "label": "NEUTRAL"
        },
        {
          "date": "2026-06-17",
          "score": 25,
          "label": "WEAK BULLISH"
        },
        {
          "date": "2026-06-18",
          "score": 0,
          "label": "NEUTRAL"
        },
        {
          "date": "2026-06-19",
          "score": 0,
          "label": "NEUTRAL"
        },
        {
          "date": "2026-06-22",
          "score": -25,
          "label": "WEAK BEARISH"
        },
        {
          "date": "2026-06-23",
          "score": 25,
          "label": "WEAK BULLISH"
        },
        {
          "date": "2026-06-24",
          "score": 0,
          "label": "NEUTRAL"
        },
        {
          "date": "2026-06-25",
          "score": -25,
          "label": "WEAK BEARISH"
        },
        {
          "date": "2026-06-26",
          "score": -25,
          "label": "WEAK BEARISH"
        },
        {
          "date": "2026-06-29",
          "score": 0,
          "label": "NEUTRAL"
        },
        {
          "date": "2026-06-30",
          "score": -25,
          "label": "WEAK BEARISH"
        }
      ]
    },
    "candle_patterns": [
      {
        "name": "Hammer 🔨",
        "type": "bullish",
        "desc": "Tín hiệu đảo chiều tăng tiềm năng"
      }
    ],
    "sr_zones": [
      {
        "level": 1845.95,
        "type": "support",
        "strength": 1,
        "dist_pct": -0.62,
        "near": true
      },
      {
        "level": 1894.22,
        "type": "resistance",
        "strength": 2,
        "dist_pct": 1.98,
        "near": false
      },
      {
        "level": 1917.0,
        "type": "resistance",
        "strength": 3,
        "dist_pct": 3.21,
        "near": false
      },
      {
        "level": 1792.08,
        "type": "support",
        "strength": 3,
        "dist_pct": -3.52,
        "near": false
      },
      {
        "level": 1773.88,
        "type": "support",
        "strength": 2,
        "dist_pct": -4.5,
        "near": false
      },
      {
        "level": 1742.12,
        "type": "support",
        "strength": 2,
        "dist_pct": -6.21,
        "near": false
      }
    ],
    "sector_heatmap": [
      {
        "sector": "Hóa chất",
        "avg_change": 1.13,
        "count": 9
      },
      {
        "sector": "Dầu khí",
        "avg_change": 0.37,
        "count": 3
      },
      {
        "sector": "Bán lẻ",
        "avg_change": 0.35,
        "count": 4
      },
      {
        "sector": "Hàng & Dịch vụ Công nghiệp",
        "avg_change": 0.26,
        "count": 10
      },
      {
        "sector": "Ngân hàng",
        "avg_change": 0.22,
        "count": 20
      },
      {
        "sector": "Tài nguyên Cơ bản",
        "avg_change": 0.17,
        "count": 7
      },
      {
        "sector": "Bất động sản",
        "avg_change": 0.11,
        "count": 24
      },
      {
        "sector": "Xây dựng và Vật liệu",
        "avg_change": 0.1,
        "count": 16
      },
      {
        "sector": "Dịch vụ tài chính",
        "avg_change": 0.07,
        "count": 15
      },
      {
        "sector": "Du lịch và Giải trí",
        "avg_change": 0.01,
        "count": 3
      },
      {
        "sector": "Ô tô và phụ tùng",
        "avg_change": 0.0,
        "count": 1
      },
      {
        "sector": "Điện, nước & xăng dầu khí đốt",
        "avg_change": -0.01,
        "count": 11
      },
      {
        "sector": "Thực phẩm và đồ uống",
        "avg_change": -0.12,
        "count": 16
      },
      {
        "sector": "Y tế",
        "avg_change": -0.18,
        "count": 2
      },
      {
        "sector": "Hàng cá nhân & Gia dụng",
        "avg_change": -0.21,
        "count": 7
      },
      {
        "sector": "Công nghệ Thông tin",
        "avg_change": -0.25,
        "count": 3
      },
      {
        "sector": "Bảo hiểm",
        "avg_change": -1.06,
        "count": 3
      }
    ]
  },
  "VN30": {
    "symbol": "VN30",
    "date": "2026-06-30 10:29 (ICT)",
    "close": 2002.04,
    "change": -2.25,
    "change_pc": -0.11225920400740412,
    "volume": 56865538.0,
    "technical": {
      "ma20": 1975.003,
      "pivot": 2004.6166666666668,
      "cmf": 0.02160766263055404,
      "adx": 20.652639406632908
    },
    "general_markdown": "### 1. Diễn biến phiên giao dịch\nVN30 đóng cửa tại 2002.04, biến động nhẹ so với tham chiếu. Khối lượng khớp lệnh đạt 56.866 triệu CP, thấp hơn 79.93% so với trung bình 20 phiên.\n\n### 2. Xu hướng & Động lượng\n- Xu hướng MA: Ngắn hạn (MA10, MA20) tăng; Trung hạn (MA50) giảm; Dài hạn (MA100, MA200) tăng.\n- ROC10 = +2.13%, ROC20 = +1.47%: Động lượng tích cực.\n- Nhận xét tổng hợp: Xu hướng phân kỳ (ngắn=up, trung=down, dài=up), động lượng tích cực nhưng cần thêm tín hiệu xác nhận.\n\n### 3. Nhận định Xu hướng Tổng hợp\n- **Mở đầu:** Thị trường đang trong vùng phân kỳ xu hướng (ngắn=up, trung=down, dài=up), động lượng tích cực từ ROC nhưng MA trung hạn vẫn giảm gây nhiễu.\n- **Độ rộng thị trường:** Bên mua chiếm ưu thế rõ rệt với tỷ lệ A/D là 4.0 (16 mã tăng, 4 mã giảm), đà tăng lan tỏa rộng.\n- **Thanh khoản:** Khối lượng chỉ đạt 56.87 triệu CP, thấp hơn 79.93% so với TB 20 phiên, phản ánh tâm lý thận trọng của dòng tiền.\n- **Sức khỏe thị trường:** 0% mã trên MA200 cho thấy phục hồi chưa lan tỏa đến dài hạn. Tỷ lệ A/D cao (4.0) nhưng giá đang ở dưới MA50, cho thấy đà phục hồi chưa bền vững.\n- **Khuyến nghị hành động:**\n  - *Cảnh báo:* ADX ở mức 20.7 (trung bình) và CMF dương nhẹ (0.0216) cho thấy xu hướng chưa mạnh và dòng tiền vào yếu.\n  - *Chiến lược:* Chờ tín hiệu.\n- **Kết luận:** ➡️ **Chờ tín hiệu** — thị trường tích cực nhưng thanh khoản thấp và xu hướng trung hạn giảm gây rủi ro.\n\n### 4. Thống kê Cổ phiếu & Nhóm ngành\n- **Top 5 tăng mạnh nhất (VN30):** BCM (+0.96%), GVR (+0.77%), NVL (+0.40%), HDB (+0.39%), SHB (+0.37%)\n- **Top 5 giảm mạnh nhất (VN30):** TPB (0.00%), VJC (-0.07%), MWG (-0.25%), VIC (-0.55%), BVH (-0.77%)\n- **Ngành thu hút dòng tiền:** Cao su - Gỗ (+0.77%), Thép - Xây dựng (+0.21%), Chứng khoán (+0.19%), Ngân hàng (+0.17%), Bất động sản (+0.16%), Công nghệ - Viễn thông (+0.14%), Dầu khí (+0.13%), Bán lẻ - Tiêu dùng (+0.02%)\n- **Ngành bị rút dòng tiền:** Vận tải - Logistics (-0.07%), Bảo hiểm (-0.77%)\n\n### 5. Market Breadth & Độ rộng thị trường\nSố mã tăng: 16, giảm: 4, đứng: 10. Tỷ lệ A/D: 4.0. Độ rộng thị trường tích cực khi số mã tăng áp đảo giảm, cho thấy sự phân hóa thấp và đà tăng lan tỏa tốt.",
    "scenario_markdown": "### 1. KỊCH BẢN TÍCH CỰC (Xác suất cao nhất)\n* **Xác suất xảy ra:** 45%\n* **Độ tin cậy:** 6/10\n\n**Điều kiện kích hoạt:**\n- Giá vượt dứt khoát kháng cự MA50 (2006.27) với độ rộng thị trường tích cực.\n- Khối lượng gia tăng vượt TB 20 phiên, xác nhận dòng tiền quay trở lại.\n\n### 2. KỊCH BẢN TRUNG TÍNH (Dao động trong range 1975.00 - 2006.27)\n* **Xác suất xảy ra:** 40%\n* **Độ tin cậy:** 7/10\n\n**Điều kiện kích hoạt:**\n- Giá tiếp tục dao động, không thể vượt MA50 (2006.27) nhưng cũng không thủng MA20 (1975.00).\n- Biến động duy trì ở mức LOW_VOL và Trend Agreement Score duy trì dưới mức 50.\n\n### 3. KỊCH BẢN TIÊU CỰC\n* **Xác suất xảy ra:** 15%\n* **Độ tin cậy:** 5/10\n\n**Điều kiện kích hoạt:**\n- Giá thủng dứt khoát hỗ trợ MA20 (1975.00) với khối lượng lớn, độ rộng thị trường tiêu cực.\n- CMF chuyển âm, xác nhận dòng tiền rút ra.\n\n### Dẫn chứng chung cho các kịch bản:\n- **Volatility regime = LOW_VOL:** Biên độ dao động (20 phiên) ≈ 4.25% của giá, hỗ trợ cho kịch bản sideway biên độ hẹp.\n- **Trend agreement score = 33/100 (WEAK BULLISH):** Cho thấy xu hướng tăng yếu chi phối, khiến mọi đợt chỉnh khó bền vững.\n- **Khoảng đệm kỹ thuật:** Khoảng cách tới hỗ trợ MA20 (1975.00) là -1.37% và kháng cự MA50 (2006.27) là +0.21% cho thấy thị trường đang ở vị trí sát vùng ranh giới quan trọng.\n- **Horizon (Tầm nhìn):** 5-15 phiên.",
    "volume_markdown": "### 1. Thống kê Chỉ báo Khối lượng\n| Chỉ báo | Giá trị | Nhận định |\n|---|---|---|\n| CMF | 0.0216 | Dòng tiền vào nhẹ (trên 0) |\n| VWAP | 1977.90 | Giá hiện tại (2002.04) trên VWAP, cho thấy giá đang được hỗ trợ bởi dòng tiền |\n| OBV | 14836499370 | - |\n\n### 2. Nhận định Dòng tiền\nDòng tiền ròng vào nhẹ (CMF = 0.0216). Giá đóng cửa trên VWAP cho thấy áp lực mua chiếm ưu thế. Không có dấu hiệu phân phối rõ rệt.",
    "trend_markdown": "### 1. Thống kê Xu hướng & Động lượng\n| Chỉ báo | Giá trị | Khoảng cách % | Vai trò |\n|---|---|---|---|\n| MA10 | 1989.29 | +0.64% | Hỗ trợ |\n| MA20 | 1975.00 | +1.37% | Hỗ trợ |\n| MA50 | 2006.27 | -0.21% | Kháng cự |\n| MA100 | 1960.93 | +2.10% | Hỗ trợ |\n| MA200 | 1951.30 | +2",
    "tas": {
      "score": 33,
      "label": "WEAK BULLISH",
      "total_raw": 3,
      "max_raw": 9,
      "indicators": [
        {
          "group": "Cấu trúc (MA)",
          "name": "Giá vs MA20 (1975)",
          "status": "Bullish",
          "score": 1
        },
        {
          "group": "Cấu trúc (MA)",
          "name": "Giá vs MA50 (2006)",
          "status": "Bearish",
          "score": -1
        },
        {
          "group": "Cấu trúc (MA)",
          "name": "Giá vs MA200 (1951)",
          "status": "Bullish",
          "score": 1
        },
        {
          "group": "Động lượng",
          "name": "ROC10 (+2.1%)",
          "status": "Bullish",
          "score": 1
        },
        {
          "group": "Động lượng",
          "name": "ROC20 (+1.5%)",
          "status": "Neutral",
          "score": 0
        },
        {
          "group": "Động lượng",
          "name": "Keltner (1955–1995)",
          "status": "Bullish",
          "score": 1
        },
        {
          "group": "Dòng tiền",
          "name": "CMF (+0.022)",
          "status": "Neutral",
          "score": 0
        },
        {
          "group": "Dòng tiền",
          "name": "Giá vs VWAP (1978)",
          "status": "Bullish",
          "score": 1
        },
        {
          "group": "Dòng tiền",
          "name": "Vol vs MA20 (-80%)",
          "status": "Bearish",
          "score": -1
        }
      ],
      "history": [
        {
          "date": "2026-06-03",
          "score": 0,
          "label": "NEUTRAL"
        },
        {
          "date": "2026-06-04",
          "score": 0,
          "label": "NEUTRAL"
        },
        {
          "date": "2026-06-05",
          "score": -25,
          "label": "WEAK BEARISH"
        },
        {
          "date": "2026-06-08",
          "score": 0,
          "label": "NEUTRAL"
        },
        {
          "date": "2026-06-09",
          "score": -25,
          "label": "WEAK BEARISH"
        },
        {
          "date": "2026-06-10",
          "score": -25,
          "label": "WEAK BEARISH"
        },
        {
          "date": "2026-06-11",
          "score": -25,
          "label": "WEAK BEARISH"
        },
        {
          "date": "2026-06-12",
          "score": 0,
          "label": "NEUTRAL"
        },
        {
          "date": "2026-06-15",
          "score": 25,
          "label": "WEAK BULLISH"
        },
        {
          "date": "2026-06-16",
          "score": -25,
          "label": "WEAK BEARISH"
        },
        {
          "date": "2026-06-17",
          "score": 25,
          "label": "WEAK BULLISH"
        },
        {
          "date": "2026-06-18",
          "score": -25,
          "label": "WEAK BEARISH"
        },
        {
          "date": "2026-06-19",
          "score": 0,
          "label": "NEUTRAL"
        },
        {
          "date": "2026-06-22",
          "score": -25,
          "label": "WEAK BEARISH"
        },
        {
          "date": "2026-06-23",
          "score": 25,
          "label": "WEAK BULLISH"
        },
        {
          "date": "2026-06-24",
          "score": 0,
          "label": "NEUTRAL"
        },
        {
          "date": "2026-06-25",
          "score": -25,
          "label": "WEAK BEARISH"
        },
        {
          "date": "2026-06-26",
          "score": -25,
          "label": "WEAK BEARISH"
        },
        {
          "date": "2026-06-29",
          "score": -25,
          "label": "WEAK BEARISH"
        },
        {
          "date": "2026-06-30",
          "score": -25,
          "label": "WEAK BEARISH"
        }
      ]
    },
    "candle_patterns": [
      {
        "name": "Evening Star 🌆",
        "type": "bearish",
        "desc": "Sao hôm — khả năng đảo chiều giảm trung hạn"
      }
    ],
    "sr_zones": [
      {
        "level": 2011.62,
        "type": "resistance",
        "strength": 2,
        "dist_pct": 0.48,
        "near": true
      },
      {
        "level": 1971.22,
        "type": "support",
        "strength": 2,
        "dist_pct": -1.54,
        "near": false
      },
      {
        "level": 2050.89,
        "type": "resistance",
        "strength": 3,
        "dist_pct": 2.44,
        "near": false
      },
      {
        "level": 1934.64,
        "type": "support",
        "strength": 2,
        "dist_pct": -3.37,
        "near": false
      },
      {
        "level": 2075.09,
        "type": "resistance",
        "strength": 3,
        "dist_pct": 3.65,
        "near": false
      },
      {
        "level": 2108.63,
        "type": "resistance",
        "strength": 3,
        "dist_pct": 5.32,
        "near": false
      }
    ],
    "sector_heatmap": [
      {
        "sector": "Hóa chất",
        "avg_change": 1.13,
        "count": 9
      },
      {
        "sector": "Dầu khí",
        "avg_change": 0.37,
        "count": 3
      },
      {
        "sector": "Bán lẻ",
        "avg_change": 0.35,
        "count": 4
      },
      {
        "sector": "Hàng & Dịch vụ Công nghiệp",
        "avg_change": 0.26,
        "count": 10
      },
      {
        "sector": "Ngân hàng",
        "avg_change": 0.22,
        "count": 20
      },
      {
        "sector": "Tài nguyên Cơ bản",
        "avg_change": 0.17,
        "count": 7
      },
      {
        "sector": "Bất động sản",
        "avg_change": 0.11,
        "count": 24
      },
      {
        "sector": "Xây dựng và Vật liệu",
        "avg_change": 0.1,
        "count": 16
      },
      {
        "sector": "Dịch vụ tài chính",
        "avg_change": 0.07,
        "count": 15
      },
      {
        "sector": "Du lịch và Giải trí",
        "avg_change": 0.01,
        "count": 3
      },
      {
        "sector": "Ô tô và phụ tùng",
        "avg_change": 0.0,
        "count": 1
      },
      {
        "sector": "Điện, nước & xăng dầu khí đốt",
        "avg_change": -0.01,
        "count": 11
      },
      {
        "sector": "Thực phẩm và đồ uống",
        "avg_change": -0.12,
        "count": 16
      },
      {
        "sector": "Y tế",
        "avg_change": -0.18,
        "count": 2
      },
      {
        "sector": "Hàng cá nhân & Gia dụng",
        "avg_change": -0.21,
        "count": 7
      },
      {
        "sector": "Công nghệ Thông tin",
        "avg_change": -0.25,
        "count": 3
      },
      {
        "sector": "Bảo hiểm",
        "avg_change": -1.06,
        "count": 3
      }
    ]
  },
  "VN100": {
    "symbol": "VN100",
    "date": "2026-06-30 10:29 (ICT)",
    "close": 1934.1,
    "change": 0.9299999999998363,
    "change_pc": 0.04810751253122262,
    "volume": 141442672.0,
    "technical": {
      "ma20": 1901.1889999999999,
      "pivot": 1933.756666666667,
      "cmf": 0.09624061600874873,
      "adx": 23.895491589405076
    },
    "general_markdown": "### 1. Diễn biến phiên giao dịch\nGiá đóng cửa 1934.10, biến động nhẹ từ mức mở 1933.79. Khối lượng khớp lệnh 141.443 triệu CP, thấp hơn 73.70% so với TB 20 phiên, cho thấy thanh khoản suy giảm mạnh.\n\n### 2. Xu hướng & Động lượng\n- MA10, MA20: xu hướng tăng (ngắn hạn)\n- MA50: xu hướng tăng (trung hạn)\n- MA100, MA200: xu hướng tăng (dài hạn)\n- ROC10 = +2.44%, ROC20 = +2.11%: động lượng tích cực ở cả ngắn và trung hạn\n- Kết hợp: VN100 trên tất cả MAs, xu hướng tăng đồng thuận toàn bộ khung thời gian\n\n### 3. Nhận định Xu hướng Tổng hợp\n**Mở đầu:** VN100 trên tất cả MAs — xu hướng tăng đồng thuận toàn bộ khung thời gian, được hỗ trợ bởi ROC10 (+2.44%) và ROC20 (+2.11%) tích cực.\n**Độ rộng thị trường:** 44 mã tăng, 16 mã giảm, tỷ lệ A/D 2.75, cho thấy đà tăng lan tỏa mạnh, bên mua chiếm ưu thế.\n**Thanh khoản:** Khối lượng 141.44 triệu CP, thấp hơn 73.70% so TB 20 phiên, phản ánh tâm lý thận trọng của dòng tiền dù giá tăng.\n**Sức khỏe thị trường:** Tỷ lệ A/D 2.75 và giá trên tất cả MAs cho thấy đợt phục hồi có sự lan tỏa rộng, không tập trung vào một nhóm mã.\n**Khuyến nghị hành động:**\n- *Cảnh báo:* ADX = 23.9 (dưới ngưỡng mạnh) và CMF = 0.0962 (dương yếu) cho thấy sức mạnh xu hướng chưa vững chắc.\n- *Chiến lược:* Chờ tín hiệu — ưu tiên quan sát do thanh khoản thấp và ADX chưa đủ mạnh.\n**Kết luận:** ➡️ **Chờ tín hiệu** — thị trường tăng nhưng thiếu xác nhận từ khối lượng và ADX.\n\n### 4. Thống kê Cổ phiếu & Nhóm ngành\n- Top 5 tăng mạnh nhất (VN100): NKG (+2.08%), OCB (+1.83%), CTD (+1.25%), BWE (+1.11%), DPM (+1.09%)\n- Top 5 giảm mạnh nhất (VN100): KDC (-0.60%), HDG (-0.72%), BVH (-0.77%), BAF (-0.85%), EVF (-1.14%)\n- Nhóm ngành thu hút dòng tiền: Cao su - Gỗ (+0.77%), Thép - Xây dựng (+0.47%), Hóa chất - Phân bón (+0.41%)\n- Nhóm ngành bị rút dòng tiền: Bán lẻ - Tiêu dùng (-0.12%), Điện - Nước - Khí (-0.12%), Bảo hiểm (-0.77%)\n\n### 5. Market Breadth & Độ rộng thị trường\n- VN100: 44 mã tăng, 16 mã giảm, 29 mã đứng, tỷ lệ A/D 2.75 — bên mua chiếm ưu thế.\n- VN30: 16/30 mã tăng (53.3%), 4/30 mã giảm (13.3%), 10/30 mã đứng, tỷ lệ A/D 4.0 — độ phân hóa thấp, tập trung vào nhóm tăng.",
    "scenario_markdown": "### 1. KỊCH BẢN TÍCH CỰC\n* **Xác suất xảy ra:** 20%\n* **Độ tin cậy:** 6/10\n\n**Điều kiện kích hoạt:**\n- Giá vượt dứt khoát kháng cự 1956.15 với độ rộng thị trường tích cực (A/D > 2).\n- Khối lượng cải thiện vượt TB 20 phiên, xác nhận dòng tiền tham gia.\n\n### 2. KỊCH BẢN TRUNG TÍNH (Dao động trong range 1905.52 - 1956.15) (Xác suất cao nhất)\n* **Xác suất xảy ra:** 55%\n* **Độ tin cậy:** 8/10\n\n**Điều kiện kích hoạt:**\n- Giá tiếp tục dao động trong range 1905.52 - 1956.15, không thể vượt 1956.15 nhưng cũng không thủng 1905.52.\n- Khối lượng duy trì ở mức thấp dưới TB 20 phiên, Trend Agreement Score duy trì trên 50.\n\n### 3. KỊCH BẢN TIÊU CỰC\n* **Xác suất xảy ra:** 25%\n* **Độ tin cậy:** 7/10\n\n**Điều kiện kích hoạt:**\n- Giá thủng dứt khoát hỗ trợ 1905.52 với khối lượng lớn, độ rộng thị trường tiêu cực (A/D < 1).\n- ADX giảm dưới 20, báo hiệu xu hướng tăng suy yếu.\n\n### Dẫn chứng chung cho các kịch bản:\n- **Volatility regime = LOW_VOL:** Biên độ dao động (20 phiên) ≈ 4.99% của giá, hỗ trợ cho kịch bản sideway biên độ rộng.\n- **Trend agreement score = 78/100 (STRONG BULLISH):** Cho thấy xu hướng tăng vẫn chi phối, khiến mọi đợt chỉnh khó bền vững.\n- **Khoảng đệm kỹ thuật:** Khoảng cách tới hỗ trợ/kháng cự hiện tại là -1.48% / 1.14% cho thấy thị trường đang ở vị trí sát vùng ranh giới quan trọng.\n- **Horizon (Tầm nhìn):** 5-15 phiên.",
    "volume_markdown": "### 1. Thống kê Chỉ báo Khối lượng\n| Chỉ báo | Giá trị | Nhận định |\n|---|---|---|\n| CMF | 0.0962 | Dòng tiền vào yếu, trên 0 nhưng thấp |\n| VWAP | 1905.80 | Giá (1934.10) đang trên VWAP, phản ánh lực mua chiếm ưu thế |\n| OBV | 48193942867 | Chưa có dấu hiệu phân phối rõ rệt |\n\n### 2. Nhận định Dòng tiền\nDòng tiền ròng vào nhẹ (CMF = 0.0962), giá đang trên VWAP cho thấy áp lực mua chiếm ưu thế. Tuy nhiên, khối lượng thấp hơn 73.70% so TB 20 phiên, không có dấu hiệu phân phối rõ ràng.",
    "trend_markdown": "### 1. Thống kê Xu hướng & Động lượng\n| Chỉ báo | Giá trị | Khoảng cách % tới giá | Nhận xét |\n|---|---|---|---|\n| MA10 | 1920.34 | +0.72% | Hỗ trợ ngắn hạn |\n| MA20 | 1901.19 | +1.73% | Hỗ trợ ngắn hạn |\n| MA50 | 1931.29 | +0",
    "tas": {
      "score": 78,
      "label": "STRONG BULLISH",
      "total_raw": 7,
      "max_raw": 9,
      "indicators": [
        {
          "group": "Cấu trúc (MA)",
          "name": "Giá vs MA20 (1901)",
          "status": "Bullish",
          "score": 1
        },
        {
          "group": "Cấu trúc (MA)",
          "name": "Giá vs MA50 (1931)",
          "status": "Bullish",
          "score": 1
        },
        {
          "group": "Cấu trúc (MA)",
          "name": "Giá vs MA200 (1866)",
          "status": "Bullish",
          "score": 1
        },
        {
          "group": "Động lượng",
          "name": "ROC10 (+2.4%)",
          "status": "Bullish",
          "score": 1
        },
        {
          "group": "Động lượng",
          "name": "ROC20 (+2.1%)",
          "status": "Bullish",
          "score": 1
        },
        {
          "group": "Động lượng",
          "name": "Keltner (1881–1920)",
          "status": "Bullish",
          "score": 1
        },
        {
          "group": "Dòng tiền",
          "name": "CMF (+0.096)",
          "status": "Bullish",
          "score": 1
        },
        {
          "group": "Dòng tiền",
          "name": "Giá vs VWAP (1906)",
          "status": "Bullish",
          "score": 1
        },
        {
          "group": "Dòng tiền",
          "name": "Vol vs MA20 (-74%)",
          "status": "Bearish",
          "score": -1
        }
      ],
      "history": [
        {
          "date": "2026-06-03",
          "score": -25,
          "label": "WEAK BEARISH"
        },
        {
          "date": "2026-06-04",
          "score": -25,
          "label": "WEAK BEARISH"
        },
        {
          "date": "2026-06-05",
          "score": -25,
          "label": "WEAK BEARISH"
        },
        {
          "date": "2026-06-08",
          "score": 0,
          "label": "NEUTRAL"
        },
        {
          "date": "2026-06-09",
          "score": -25,
          "label": "WEAK BEARISH"
        },
        {
          "date": "2026-06-10",
          "score": -25,
          "label": "WEAK BEARISH"
        },
        {
          "date": "2026-06-11",
          "score": -25,
          "label": "WEAK BEARISH"
        },
        {
          "date": "2026-06-12",
          "score": 0,
          "label": "NEUTRAL"
        },
        {
          "date": "2026-06-15",
          "score": 25,
          "label": "WEAK BULLISH"
        },
        {
          "date": "2026-06-16",
          "score": 0,
          "label": "NEUTRAL"
        },
        {
          "date": "2026-06-17",
          "score": 25,
          "label": "WEAK BULLISH"
        },
        {
          "date": "2026-06-18",
          "score": 0,
          "label": "NEUTRAL"
        },
        {
          "date": "2026-06-19",
          "score": 0,
          "label": "NEUTRAL"
        },
        {
          "date": "2026-06-22",
          "score": -25,
          "label": "WEAK BEARISH"
        },
        {
          "date": "2026-06-23",
          "score": 25,
          "label": "WEAK BULLISH"
        },
        {
          "date": "2026-06-24",
          "score": 0,
          "label": "NEUTRAL"
        },
        {
          "date": "2026-06-25",
          "score": -25,
          "label": "WEAK BEARISH"
        },
        {
          "date": "2026-06-26",
          "score": -25,
          "label": "WEAK BEARISH"
        },
        {
          "date": "2026-06-29",
          "score": 0,
          "label": "NEUTRAL"
        },
        {
          "date": "2026-06-30",
          "score": -25,
          "label": "WEAK BEARISH"
        }
      ]
    },
    "candle_patterns": [
      {
        "name": "Doji",
        "type": "neutral",
        "desc": "Thị trường do dự, chờ xác nhận chiều"
      }
    ],
    "sr_zones": [
      {
        "level": 1956.15,
        "type": "resistance",
        "strength": 4,
        "dist_pct": 1.14,
        "near": true
      },
      {
        "level": 1905.52,
        "type": "support",
        "strength": 3,
        "dist_pct": -1.48,
        "near": true
      },
      {
        "level": 1962.91,
        "type": "resistance",
        "strength": 4,
        "dist_pct": 1.49,
        "near": true
      },
      {
        "level": 1878.42,
        "type": "support",
        "strength": 4,
        "dist_pct": -2.88,
        "near": false
      },
      {
        "level": 2001.82,
        "type": "resistance",
        "strength": 2,
        "dist_pct": 3.5,
        "near": false
      },
      {
        "level": 1861.14,
        "type": "support",
        "strength": 4,
        "dist_pct": -3.77,
        "near": false
      }
    ],
    "sector_heatmap": [
      {
        "sector": "Hóa chất",
        "avg_change": 1.13,
        "count": 9
      },
      {
        "sector": "Dầu khí",
        "avg_change": 0.37,
        "count": 3
      },
      {
        "sector": "Bán lẻ",
        "avg_change": 0.35,
        "count": 4
      },
      {
        "sector": "Hàng & Dịch vụ Công nghiệp",
        "avg_change": 0.26,
        "count": 10
      },
      {
        "sector": "Ngân hàng",
        "avg_change": 0.22,
        "count": 20
      },
      {
        "sector": "Tài nguyên Cơ bản",
        "avg_change": 0.17,
        "count": 7
      },
      {
        "sector": "Bất động sản",
        "avg_change": 0.11,
        "count": 24
      },
      {
        "sector": "Xây dựng và Vật liệu",
        "avg_change": 0.1,
        "count": 16
      },
      {
        "sector": "Dịch vụ tài chính",
        "avg_change": 0.07,
        "count": 15
      },
      {
        "sector": "Du lịch và Giải trí",
        "avg_change": 0.01,
        "count": 3
      },
      {
        "sector": "Ô tô và phụ tùng",
        "avg_change": 0.0,
        "count": 1
      },
      {
        "sector": "Điện, nước & xăng dầu khí đốt",
        "avg_change": -0.01,
        "count": 11
      },
      {
        "sector": "Thực phẩm và đồ uống",
        "avg_change": -0.12,
        "count": 16
      },
      {
        "sector": "Y tế",
        "avg_change": -0.18,
        "count": 2
      },
      {
        "sector": "Hàng cá nhân & Gia dụng",
        "avg_change": -0.21,
        "count": 7
      },
      {
        "sector": "Công nghệ Thông tin",
        "avg_change": -0.25,
        "count": 3
      },
      {
        "sector": "Bảo hiểm",
        "avg_change": -1.06,
        "count": 3
      }
    ]
  }
}